Workbook

Sheet Resultado e caixa
A1: Linha | B1: Mês 1 | C1: Mês 2 | D1: Mês 3 | E1: Mês 4 | F1: Mês 5 | G1: Mês 6 | H1: Total
A2: Clientes ativos (fim do mês) | B2: 8 | C2: 22 | D2: 40 | E2: 62 | F2: 90 | G2: 107
A3: Clientes novos | B3: =B2 | C3: =C2-B2 | D3: =D2-C2 | E3: =E2-D2 | F3: =F2-E2 | G3: =G2-F2
A4: Receita recorrente (MRR) | B4: =B2*Premissas!$B$3 | C4: =C2*Premissas!$B$3 | D4: =D2*Premissas!$B$3 | E4: =E2*Premissas!$B$3 | F4: =F2*Premissas!$B$3 | G4: =G2*Premissas!$B$3 | H4: =SUM(B4:G4)
A5: Receita de setup | B5: =B3*Premissas!$B$4*Premissas!$B$5 | C5: =C3*Premissas!$B$4*Premissas!$B$5 | D5: =D3*Premissas!$B$4*Premissas!$B$5 | E5: =E3*Premissas!$B$4*Premissas!$B$5 | F5: =F3*Premissas!$B$4*Premissas!$B$5 | G5: =G3*Premissas!$B$4*Premissas!$B$5 | H5: =SUM(B5:G5)
A6: RECEITA TOTAL | B6: =B4+B5 | C6: =C4+C5 | D6: =D4+D5 | E6: =E4+E5 | F6: =F4+F5 | G6: =G4+G5 | H6: =SUM(B6:G6)
A7: (-) Custo variável dos clientes | B7: =-B2*Premissas!$B$6 | C7: =-C2*Premissas!$B$6 | D7: =-D2*Premissas!$B$6 | E7: =-E2*Premissas!$B$6 | F7: =-F2*Premissas!$B$6 | G7: =-G2*Premissas!$B$6 | H7: =SUM(B7:G7)
A8: (-) Taxa do gateway | B8: =-B6*Premissas!$B$7 | C8: =-C6*Premissas!$B$7 | D8: =-D6*Premissas!$B$7 | E8: =-E6*Premissas!$B$7 | F8: =-F6*Premissas!$B$7 | G8: =-G6*Premissas!$B$7 | H8: =SUM(B8:G8)
A9: (-) Custo operacional | B9: =-'Custos mensais'!D17 | C9: =-'Custos mensais'!E17 | D9: =-'Custos mensais'!F17 | E9: =-'Custos mensais'!G17 | F9: =-'Custos mensais'!H17 | G9: =-'Custos mensais'!I17 | H9: =SUM(B9:G9)
A10: (-) Mídia | B10: =-'Custos mensais'!D18 | C10: =-'Custos mensais'!E18 | D10: =-'Custos mensais'!F18 | E10: =-'Custos mensais'!G18 | F10: =-'Custos mensais'!H18 | G10: =-'Custos mensais'!I18 | H10: =SUM(B10:G10)
A11: RESULTADO ANTES DO IR | B11: =B6+B7+B8+B9+B10 | C11: =C6+C7+C8+C9+C10 | D11: =D6+D7+D8+D9+D10 | E11: =E6+E7+E8+E9+E10 | F11: =F6+F7+F8+F9+F10 | G11: =G6+G7+G8+G9+G10 | H11: =SUM(B11:G11)
A12: (-) Provisão IR (se positivo) | B12: =-MAX(0,B11)*Premissas!$B$8 | C12: =-MAX(0,C11)*Premissas!$B$8 | D12: =-MAX(0,D11)*Premissas!$B$8 | E12: =-MAX(0,E11)*Premissas!$B$8 | F12: =-MAX(0,F11)*Premissas!$B$8 | G12: =-MAX(0,G11)*Premissas!$B$8 | H12: =SUM(B12:G12)
A13: RESULTADO LÍQUIDO | B13: =B11+B12 | C13: =C11+C12 | D13: =D11+D12 | E13: =E11+E12 | F13: =F11+F12 | G13: =G11+G12 | H13: =SUM(B13:G13)
A14: CAIXA ACUMULADO | B14: =B13 | C14: =B14+C13 | D14: =C14+D13 | E14: =D14+E13 | F14: =E14+F13 | G14: =F14+G13
A15: INVESTIMENTO NECESSÁRIO NO MÊS (aporte) | B15: =MAX(0,-B13) | C15: =MAX(0,-C13) | D15: =MAX(0,-D13) | E15: =MAX(0,-E13) | F15: =MAX(0,-F13) | G15: =MAX(0,-G13) | H15: =SUM(B15:G15)
A16: CAC (mídia + ligações ÷ clientes novos) | B16: =IF(B3>0,(-B10+'Custos mensais'!D15)/B3,0) | C16: =IF(C3>0,(-C10+'Custos mensais'!E15)/C3,0) | D16: =IF(D3>0,(-D10+'Custos mensais'!F15)/D3,0) | E16: =IF(E3>0,(-E10+'Custos mensais'!G15)/E3,0) | F16: =IF(F3>0,(-F10+'Custos mensais'!H15)/F3,0) | G16: =IF(G3>0,(-G10+'Custos mensais'!I15)/G3,0)
A18: INVESTIMENTO TOTAL ATÉ SE PAGAR (pior caixa acumulado) | B18: =-MIN(0,MIN(B14:G14))
A19: Primeiro mês com resultado líquido positivo | B19: =IFERROR(INDEX(B1:G1,MATCH(TRUE,INDEX(B13:G13>0,0),0)),"após mês 6")
A21: Células amarelas são editáveis. Clientes ativos seguem o plano do README; se a venda atrasar, reduza aqui e veja o aporte subir.

Sheet Premissas
A1: Premissa | B1: Valor | C1: Observação
A2: Câmbio US$ → R$ | B2: 5.5 | C2: Ajuste conforme a cotação
A3: Ticket médio mensal por cliente (R$) | B3: 470 | C3: Mix Essencial 297 / Pro 597 / Rede 897
A4: Setup por cliente novo (R$) | B4: 497 | C4: Metade dos clientes paga (anual isenta)
A5: % de clientes que pagam setup | B5: 0.5
A6: Custo variável por cliente/mês (R$) | B6: 110 | C6: WhatsApp API + IA da recepcionista + infra
A7: Taxa do gateway Asaas (% da receita) | B7: 0.035 | C7: Média Pix/boleto/cartão
A8: Provisão IR no CPF (% do lucro) | B8: 0.275 | C8: Carnê-leão, alíquota máxima; vira Simples com CNPJ
A9: Custo de voz por minuto (US$) | B9: 0.12 | C9: ElevenLabs Agents + telefonia
A10: Minutos por ligação | B10: 3

Sheet Custos mensais
A1: Categoria | B1: Item | C1: Unid. | D1: Mês 1 | E1: Mês 2 | F1: Mês 3 | G1: Mês 4 | H1: Mês 5 | I1: Mês 6 | J1: Total 6 meses | K1: Observação
A2: Ferramentas | B2: n8n (plano Starter) | C2: R$ | D2: 150 | E2: 150 | F2: 150 | G2: 150 | H2: 150 | I2: 150 | J2: =IF(C2="R$",SUM(D2:I2),"") | K2: Já existe; ajuste ao seu plano real
A3: Ferramentas | B3: Claude para os agentes internos | C3: US$ | D3: 40 | E3: 50 | F3: 60 | G3: 70 | H3: 80 | I3: 90 | J3: =IF(C3="R$",SUM(D3:I3),"") | K3: Via créditos do n8n ou API; cresce com o volume
A4: Ferramentas | B4: ElevenLabs (voz, plano Creator → Pro) | C4: US$ | D4: 22 | E4: 22 | F4: 99 | G4: 99 | H4: 99 | I4: 99 | J4: =IF(C4="R$",SUM(D4:I4),"") | K4: Pro no mês 3 para mais minutos/vozes
A5: Ferramentas | B5: Domínio + landing (Vercel grátis) | C5: R$ | D5: 40 | E5: 0 | F5: 0 | G5: 0 | H5: 0 | I5: 0 | J5: =IF(C5="R$",SUM(D5:I5),"") | K5: Domínio anual
A6: Telefonia | B6: Chip WhatsApp da empresa | C6: R$ | D6: 20 | E6: 20 | F6: 20 | G6: 20 | H6: 20 | I6: 20 | J6: =IF(C6="R$",SUM(D6:I6),"")
A7: Telefonia | B7: Número BR para ligações (Twilio/SIP) | C7: R$ | D7: 0 | E7: 50 | F7: 50 | G7: 50 | H7: 50 | I7: 50 | J7: =IF(C7="R$",SUM(D7:I7),"") | K7: A partir da Fase 2
A8: Telefonia | B8: Ligações de venda (nº de ligações) | C8: lig. | D8: 0 | E8: 100 | F8: 300 | G8: 500 | H8: 600 | I8: 600 | J8: =IF(C8="R$",SUM(D8:I8),"") | K8: Edite o volume; custo calculado abaixo
A9: Mídia | B9: Meta Ads | C9: R$ | D9: 1500 | E9: 2500 | F9: 4000 | G9: 6000 | H9: 8000 | I9: 9000 | J9: =IF(C9="R$",SUM(D9:I9),"") | K9: Principal alavanca; só sobe com CAC na meta
A10: Administrativo | B10: Contador (após CNPJ) | C10: R$ | D10: 0 | E10: 0 | F10: 300 | G10: 300 | H10: 300 | I10: 300 | J10: =IF(C10="R$",SUM(D10:I10),"") | K10: CNPJ previsto no fim do mês 2
A11: Administrativo | B11: Abertura do CNPJ (único) | C11: R$ | D11: 0 | E11: 0 | F11: 400 | G11: 0 | H11: 0 | I11: 0 | J11: =IF(C11="R$",SUM(D11:I11),"") | K11: Estimativa
A12: Reserva | B12: Imprevistos (10% dos custos fixos acima) | C12: R$ | D12: =0.1*(D2+D5+D6+D7+D10+D11+SUM(D13:D15)) | E12: =0.1*(E2+E5+E6+E7+E10+E11+SUM(E13:E15)) | F12: =0.1*(F2+F5+F6+F7+F10+F11+SUM(F13:F15)) | G12: =0.1*(G2+G5+G6+G7+G10+G11+SUM(G13:G15)) | H12: =0.1*(H2+H5+H6+H7+H10+H11+SUM(H13:H15)) | I12: =0.1*(I2+I5+I6+I7+I10+I11+SUM(I13:I15)) | J12: =IF(C12="R$",SUM(D12:I12),"") | K12: Calculado
A13: Conversões | B13: Claude (R$) | C13: R$ | D13: =D3*Premissas!$B$2 | E13: =E3*Premissas!$B$2 | F13: =F3*Premissas!$B$2 | G13: =G3*Premissas!$B$2 | H13: =H3*Premissas!$B$2 | I13: =I3*Premissas!$B$2 | J13: =IF(C13="R$",SUM(D13:I13),"")
A14: Conversões | B14: ElevenLabs (R$) | C14: R$ | D14: =D4*Premissas!$B$2 | E14: =E4*Premissas!$B$2 | F14: =F4*Premissas!$B$2 | G14: =G4*Premissas!$B$2 | H14: =H4*Premissas!$B$2 | I14: =I4*Premissas!$B$2 | J14: =IF(C14="R$",SUM(D14:I14),"")
A15: Conversões | B15: Custo das ligações (R$) | C15: R$ | D15: =D8*Premissas!$B$10*Premissas!$B$9*Premissas!$B$2 | E15: =E8*Premissas!$B$10*Premissas!$B$9*Premissas!$B$2 | F15: =F8*Premissas!$B$10*Premissas!$B$9*Premissas!$B$2 | G15: =G8*Premissas!$B$10*Premissas!$B$9*Premissas!$B$2 | H15: =H8*Premissas!$B$10*Premissas!$B$9*Premissas!$B$2 | I15: =I8*Premissas!$B$10*Premissas!$B$9*Premissas!$B$2 | J15: =IF(C15="R$",SUM(D15:I15),"")
J16: =IF(C16="R$",SUM(D16:I16),"")
B17: CUSTO OPERACIONAL (sem mídia) | D17: =D2+D5+D6+D7+D10+D11+D12+SUM(D13:D15) | E17: =E2+E5+E6+E7+E10+E11+E12+SUM(E13:E15) | F17: =F2+F5+F6+F7+F10+F11+F12+SUM(F13:F15) | G17: =G2+G5+G6+G7+G10+G11+G12+SUM(G13:G15) | H17: =H2+H5+H6+H7+H10+H11+H12+SUM(H13:H15) | I17: =I2+I5+I6+I7+I10+I11+I12+SUM(I13:I15) | J17: =SUM(D17:I17)
B18: MÍDIA | D18: =D9 | E18: =E9 | F18: =F9 | G18: =G9 | H18: =H9 | I18: =I9 | J18: =SUM(D18:I18)
B19: CUSTO FIXO TOTAL DO MÊS | D19: =D17+D18 | E19: =E17+E18 | F19: =F17+F18 | G19: =G17+G18 | H19: =H17+H18 | I19: =I17+I18 | J19: =SUM(D19:I19)
